pydsdl/__init__.py
pydsdl/_data_schema_builder.py
pydsdl/_data_type_builder.py
pydsdl/_dsdl.py
pydsdl/_dsdl_definition.py
pydsdl/_error.py
pydsdl/_namespace.py
pydsdl/_namespace_reader.py
pydsdl/_parser.py
pydsdl/_port_id_ranges.py
pydsdl/_test.py
pydsdl/grammar.parsimonious
pydsdl/_bit_length_set/__init__.py
pydsdl/_bit_length_set/_bit_length_set.py
pydsdl/_bit_length_set/_symbolic.py
pydsdl/_bit_length_set/_symbolic_test.py
pydsdl/_expression/__init__.py
pydsdl/_expression/_any.py
pydsdl/_expression/_container.py
pydsdl/_expression/_operator.py
pydsdl/_expression/_primitive.py
pydsdl/_expression/_test.py
pydsdl/_serializable/__init__.py
pydsdl/_serializable/_array.py
pydsdl/_serializable/_attribute.py
pydsdl/_serializable/_composite.py
pydsdl/_serializable/_name.py
pydsdl/_serializable/_primitive.py
pydsdl/_serializable/_serializable.py
pydsdl/_serializable/_void.py
pydsdl/third_party/parsimonious/__init__.py
pydsdl/third_party/parsimonious/exceptions.py
pydsdl/third_party/parsimonious/expressions.py
pydsdl/third_party/parsimonious/grammar.py
pydsdl/third_party/parsimonious/nodes.py
pydsdl/third_party/parsimonious/utils.py
pydsdl-1.24.2.dist-info/METADATA
pydsdl-1.24.2.dist-info/WHEEL
pydsdl-1.24.2.dist-info/top_level.txt
pydsdl-1.24.2.dist-info/RECORD
