Metadata-Version: 2.4
Name: pydsdl
Version: 1.24.2
Summary: Cyphal DSDL processing frontend
Home-page: https://opencyphal.org
Author: OpenCyphal
Author-email: maintainers@opencyphal.org
License: MIT
Keywords: cyphal,opencyphal,uavcan,dsdl,parser,compiler
Classifier: Intended Audience :: Developers
Classifier: Topic :: Scientific/Engineering
Classifier: Topic :: Software Development :: Embedded Systems
Classifier: Topic :: Software Development :: Libraries
Classifier: Topic :: System :: Distributed Computing
Classifier: Topic :: System :: Networking
Classifier: License :: OSI Approved :: MIT License
Classifier: Programming Language :: Python
Classifier: Programming Language :: Python :: 3
